<?xml version="1.0" encoding="UTF-8"?>
<con:soapui-project id="c0576105-fe3e-4b5b-bea8-67a57bb7cee4" created="3.10.0" activeEnvironment="Default" name="UserProject" updated="3.10.0 2021-09-14T15:18:10Z" encryptionMode="Not encrypted" abortOnError="false" runType="SEQUENTIAL" soapui-version="5.6.0" xmlns:con="http://eviware.com/soapui/config">
  <con:settings/>
  <con:interface xsi:type="con:RestService" id="64fcccb1-cfe4-4a47-b865-db96f17ed7fc" wadlVersion="http://wadl.dev.java.net/2009/02" name="https://petstore.swagger.io" type="rest" xmlns:xsi="http://www.w3.org/2001/XMLSchema-instance">
    <con:settings/>
    <con:definitionCache type="TEXT" rootPart=""/>
    <con:endpoints>
      <con:endpoint>https://petstore.swagger.io</con:endpoint>
    </con:endpoints>
    <con:resource name="User" path="/v2/user" id="d0174cf4-b145-4fae-8740-69a0bae0b549">
      <con:settings/>
      <con:parameters/>
      <con:method name="User" id="b2ba2f40-de22-4026-a0e9-6aac3d2a651e" method="POST">
        <con:settings/>
        <con:parameters/>
        <con:representation type="RESPONSE">
          <con:mediaType>application/json</con:mediaType>
          <con:status>200</con:status>
          <con:params/>
          <con:element xmlns:user="https://petstore.swagger.io/v2/user">user:Response</con:element>
        </con:representation>
        <con:representation type="REQUEST">
          <con:mediaType>application/json</con:mediaType>
          <con:params/>
        </con:representation>
        <con:request name="Request 1" id="3b8eef5a-2deb-42de-b39e-65727565d119" mediaType="application/json">
          <con:settings/>
          <con:endpoint>https://petstore.swagger.io</con:endpoint>
          <con:credentials>
            <con:selectedAuthProfile>No Authorization</con:selectedAuthProfile>
            <con:authType>No Authorization</con:authType>
          </con:credentials>
          <con:parameters/>
        </con:request>
      </con:method>
    </con:resource>
    <con:resource name="Login" path="/v2/user/login" id="6ed59afb-fe31-4bb3-9052-1aa05bf4e7ab">
      <con:settings/>
      <con:parameters/>
      <con:method name="Login" id="5fb32256-c5af-4a94-9fc3-fb20f67f286e" method="GET">
        <con:settings/>
        <con:parameters>
          <con:parameter required="true">
            <con:name>username</con:name>
            <con:value>{username}</con:value>
            <con:style>QUERY</con:style>
            <con:default>{username}</con:default>
            <con:path xsi:nil="true"/>
            <con:description xsi:nil="true"/>
          </con:parameter>
          <con:parameter required="true">
            <con:name>password</con:name>
            <con:value>{password}</con:value>
            <con:style>QUERY</con:style>
            <con:default>{password}</con:default>
            <con:path xsi:nil="true"/>
            <con:description xsi:nil="true"/>
          </con:parameter>
        </con:parameters>
        <con:representation type="RESPONSE">
          <con:mediaType>application/json</con:mediaType>
          <con:status>200</con:status>
          <con:params/>
          <con:element xmlns:log="https://petstore.swagger.io/v2/user/login">log:Response</con:element>
        </con:representation>
        <con:request name="Request 1" id="aaa68547-a313-47d6-ba6d-f6531971fb89" mediaType="application/json">
          <con:settings/>
          <con:endpoint>https://petstore.swagger.io</con:endpoint>
          <con:credentials>
            <con:selectedAuthProfile>No Authorization</con:selectedAuthProfile>
            <con:authType>No Authorization</con:authType>
          </con:credentials>
          <con:parameters>
            <con:entry key="password" value="{password}"/>
            <con:entry key="username" value="{username}"/>
          </con:parameters>
          <con:parameterOrder>
            <con:entry>username</con:entry>
            <con:entry>password</con:entry>
          </con:parameterOrder>
        </con:request>
      </con:method>
    </con:resource>
    <con:resource name="Username" path="/v2/user/{username}" id="c2f3eaf4-ffcf-4eeb-a881-d119ea058193">
      <con:settings/>
      <con:parameters/>
      <con:method name="Username" id="00a2569e-5fcb-43a5-afb3-34b1f6354d07" method="GET">
        <con:settings/>
        <con:parameters>
          <con:parameter required="true">
            <con:name>username</con:name>
            <con:value>username</con:value>
            <con:style>TEMPLATE</con:style>
            <con:default>username</con:default>
            <con:path xsi:nil="true"/>
            <con:description xsi:nil="true"/>
          </con:parameter>
        </con:parameters>
        <con:representation type="RESPONSE">
          <con:mediaType>application/json</con:mediaType>
          <con:status>200</con:status>
          <con:params/>
          <con:element xmlns:tes="https://petstore.swagger.io/v2/user/testuser8">tes:Response</con:element>
        </con:representation>
        <con:request name="Request 1" id="ac85d704-9adf-4989-b919-7e10aca5ed5d" mediaType="application/json">
          <con:settings/>
          <con:endpoint>https://petstore.swagger.io</con:endpoint>
          <con:credentials>
            <con:selectedAuthProfile>No Authorization</con:selectedAuthProfile>
            <con:authType>No Authorization</con:authType>
          </con:credentials>
          <con:parameters>
            <con:entry key="username" value="username"/>
          </con:parameters>
          <con:parameterOrder>
            <con:entry>username</con:entry>
          </con:parameterOrder>
        </con:request>
      </con:method>
      <con:method name="Username 2" id="b2a2856b-3491-4c5f-b4a8-c0a9a579e05e" method="GET">
        <con:settings/>
        <con:parameters>
          <con:parameter required="true">
            <con:name>username</con:name>
            <con:value>username</con:value>
            <con:style>TEMPLATE</con:style>
            <con:default>username</con:default>
            <con:path xsi:nil="true"/>
            <con:description xsi:nil="true"/>
          </con:parameter>
        </con:parameters>
        <con:request name="Request 1" id="fbbbb85d-d148-4fdb-b21c-e0452d9798a3" mediaType="application/json">
          <con:settings/>
          <con:endpoint>https://petstore.swagger.io</con:endpoint>
          <con:credentials>
            <con:selectedAuthProfile>No Authorization</con:selectedAuthProfile>
            <con:authType>No Authorization</con:authType>
          </con:credentials>
          <con:parameters>
            <con:entry key="username" value="username"/>
          </con:parameters>
          <con:parameterOrder>
            <con:entry>username</con:entry>
          </con:parameterOrder>
        </con:request>
      </con:method>
    </con:resource>
    <con:resource name="Logout" path="/v2/user/logout" id="5c3603c7-59fa-49ed-bea5-80f4c0159689">
      <con:settings/>
      <con:parameters/>
      <con:method name="Logout" id="e4534861-64fa-4e58-919c-60e8052f4a61" method="GET">
        <con:settings/>
        <con:parameters/>
        <con:request name="Request 1" id="cc886005-cfb9-425a-9959-1c4d9892e40b" mediaType="application/json">
          <con:settings/>
          <con:endpoint>https://petstore.swagger.io</con:endpoint>
          <con:credentials>
            <con:selectedAuthProfile>No Authorization</con:selectedAuthProfile>
            <con:authType>No Authorization</con:authType>
          </con:credentials>
          <con:parameters/>
        </con:request>
      </con:method>
    </con:resource>
  </con:interface>
  <con:testSuite id="6143e24b-26e8-460b-a27f-3de71fe7360b" name="UserProject Test Suite">
    <con:settings/>
    <con:savedRecentRuns>1</con:savedRecentRuns>
    <con:runType>SEQUENTIAL</con:runType>
    <con:testCase id="c3cbf872-6550-4526-88eb-610067ef20a7" discardOkResults="false" failOnError="true" failTestCaseOnErrors="true" keepSession="false" name="UserProject Test Case" searchProperties="true" timeout="0" maxResults="0">
      <con:settings/>
      <con:savedRecentRuns>1</con:savedRecentRuns>
      <con:testStep type="restrequest" name="POST Request" id="ea70b1f9-2acb-451e-a018-eacf5c3bf318">
        <con:settings/>
        <con:config service="https://petstore.swagger.io" resourcePath="/v2/user" methodName="User" xsi:type="con:RestRequestStep" xmlns:xsi="http://www.w3.org/2001/XMLSchema-instance">
          <con:restRequest name="POST Request" id="3b8eef5a-2deb-42de-b39e-65727565d119" mediaType="application/json" postQueryString="false">
            <con:settings>
              <con:setting id="com.eviware.soapui.impl.wsdl.WsdlRequest@request-headers">&lt;xml-fragment/></con:setting>
            </con:settings>
            <con:endpoint>https://petstore.swagger.io</con:endpoint>
            <con:request>{
    "id": 8,
    "username": "testuser8",
    "firstName": "John",
    "lastName": "Doel",
    "email": "john8@doe.com",
    "password": "testuser8",
    "phone": "234567090",
    "userStatus": 0
}</con:request>
            <con:originalUri>https://petstore.swagger.io/v2/user</con:originalUri>
            <con:assertion type="Valid HTTP Status Codes" id="06386c1a-38ea-4805-8c09-cf33d1c83f0b" name="Valid HTTP Status Codes">
              <con:settings/>
              <con:configuration>
                <codes>200</codes>
              </con:configuration>
            </con:assertion>
            <con:credentials>
              <con:selectedAuthProfile>No Authorization</con:selectedAuthProfile>
              <con:authType>No Authorization</con:authType>
            </con:credentials>
            <con:jmsConfig JMSDeliveryMode="PERSISTENT"/>
            <con:parameters/>
          </con:restRequest>
        </con:config>
      </con:testStep>
      <con:testStep type="restrequest" name="Login Request" id="d7540ae1-1303-4645-ac04-2394d8e5efeb">
        <con:settings/>
        <con:config service="https://petstore.swagger.io" resourcePath="/v2/user/login" methodName="Login" xsi:type="con:RestRequestStep" xmlns:xsi="http://www.w3.org/2001/XMLSchema-instance">
          <con:restRequest name="Login Request" id="aaa68547-a313-47d6-ba6d-f6531971fb89" mediaType="application/json">
            <con:settings>
              <con:setting id="com.eviware.soapui.impl.wsdl.WsdlRequest@request-headers">&lt;xml-fragment/></con:setting>
            </con:settings>
            <con:endpoint>https://petstore.swagger.io</con:endpoint>
            <con:request/>
            <con:originalUri>https://petstore.swagger.io/v2/user/login</con:originalUri>
            <con:assertion type="Valid HTTP Status Codes" id="79c3a316-81cb-4ed8-9c3a-abcb1056bb6c" name="Valid HTTP Status Codes">
              <con:settings/>
              <con:configuration>
                <codes>200</codes>
              </con:configuration>
            </con:assertion>
            <con:credentials>
              <con:selectedAuthProfile>No Authorization</con:selectedAuthProfile>
              <con:authType>No Authorization</con:authType>
            </con:credentials>
            <con:jmsConfig JMSDeliveryMode="PERSISTENT"/>
            <con:parameters>
              <con:entry key="password" value="testuser8"/>
              <con:entry key="username" value="testuser8"/>
            </con:parameters>
            <con:parameterOrder>
              <con:entry>username</con:entry>
              <con:entry>password</con:entry>
            </con:parameterOrder>
          </con:restRequest>
        </con:config>
      </con:testStep>
      <con:testStep type="restrequest" name="GET Request" id="9a6c7462-5e7c-4276-b82d-271169d9f137">
        <con:settings/>
        <con:config service="https://petstore.swagger.io" resourcePath="/v2/user/{username}" methodName="Username" xsi:type="con:RestRequestStep" xmlns:xsi="http://www.w3.org/2001/XMLSchema-instance">
          <con:restRequest name="GET Request" id="ac85d704-9adf-4989-b919-7e10aca5ed5d" mediaType="application/json">
            <con:settings>
              <con:setting id="com.eviware.soapui.impl.wsdl.WsdlRequest@request-headers">&lt;xml-fragment/></con:setting>
            </con:settings>
            <con:endpoint>https://petstore.swagger.io</con:endpoint>
            <con:request/>
            <con:originalUri>https://petstore.swagger.io/v2/user/testuser8</con:originalUri>
            <con:assertion type="Valid HTTP Status Codes" id="ff7f3596-8dc0-49a4-9ad8-b39b91479257" name="Valid HTTP Status Codes">
              <con:settings/>
              <con:configuration>
                <codes>200</codes>
              </con:configuration>
            </con:assertion>
            <con:credentials>
              <con:selectedAuthProfile>No Authorization</con:selectedAuthProfile>
              <con:authType>No Authorization</con:authType>
            </con:credentials>
            <con:jmsConfig JMSDeliveryMode="PERSISTENT"/>
            <con:parameters>
              <con:entry key="username" value="testuser8"/>
            </con:parameters>
            <con:parameterOrder>
              <con:entry>username</con:entry>
            </con:parameterOrder>
          </con:restRequest>
        </con:config>
      </con:testStep>
      <con:testStep type="restrequest" name="Logout Request" id="543ec591-988b-4b9c-899c-06584c7753ec">
        <con:settings/>
        <con:config service="https://petstore.swagger.io" resourcePath="/v2/user/logout" methodName="Logout" xsi:type="con:RestRequestStep" xmlns:xsi="http://www.w3.org/2001/XMLSchema-instance">
          <con:restRequest name="Logout Request" id="cc886005-cfb9-425a-9959-1c4d9892e40b" mediaType="application/json">
            <con:settings>
              <con:setting id="com.eviware.soapui.impl.wsdl.WsdlRequest@request-headers">&lt;xml-fragment/></con:setting>
            </con:settings>
            <con:endpoint>https://petstore.swagger.io</con:endpoint>
            <con:request/>
            <con:assertion type="Valid HTTP Status Codes" id="c74bfd07-c01f-4508-aca2-c2ae2fdb56fe" name="Valid HTTP Status Codes">
              <con:settings/>
              <con:configuration>
                <codes>200</codes>
              </con:configuration>
            </con:assertion>
            <con:credentials>
              <con:selectedAuthProfile>No Authorization</con:selectedAuthProfile>
              <con:authType>No Authorization</con:authType>
            </con:credentials>
            <con:jmsConfig JMSDeliveryMode="PERSISTENT"/>
            <con:parameters/>
          </con:restRequest>
        </con:config>
      </con:testStep>
      <con:testStep type="restrequest" name="Delete Request" id="7fb65c46-db15-48a2-b354-e09c75bac6e3">
        <con:settings/>
        <con:config service="https://petstore.swagger.io" resourcePath="/v2/user/{username}" methodName="Username 2" xsi:type="con:RestRequestStep" xmlns:xsi="http://www.w3.org/2001/XMLSchema-instance">
          <con:restRequest name="Delete Request" id="fbbbb85d-d148-4fdb-b21c-e0452d9798a3" mediaType="application/json">
            <con:settings>
              <con:setting id="com.eviware.soapui.impl.wsdl.WsdlRequest@request-headers">&lt;xml-fragment/></con:setting>
            </con:settings>
            <con:endpoint>https://petstore.swagger.io</con:endpoint>
            <con:request/>
            <con:assertion type="Valid HTTP Status Codes" id="1f5f5a66-1099-499c-b4af-d64085e38ec0" name="Valid HTTP Status Codes">
              <con:settings/>
              <con:configuration>
                <codes>200</codes>
              </con:configuration>
            </con:assertion>
            <con:credentials>
              <con:selectedAuthProfile>No Authorization</con:selectedAuthProfile>
              <con:authType>No Authorization</con:authType>
            </con:credentials>
            <con:jmsConfig JMSDeliveryMode="PERSISTENT"/>
            <con:parameters>
              <con:entry key="username" value="username"/>
            </con:parameters>
            <con:parameterOrder>
              <con:entry>username</con:entry>
            </con:parameterOrder>
          </con:restRequest>
        </con:config>
      </con:testStep>
      <con:properties/>
      <con:reportParameters/>
    </con:testCase>
    <con:properties/>
    <con:reportParameters/>
  </con:testSuite>
  <con:properties/>
  <con:wssContainer/>
  <con:databaseConnectionContainer/>
  <con:jmsConnectionContainer/>
  <con:oAuth2ProfileContainer/>
  <con:oAuth1ProfileContainer/>
  <con:reporting>
    <con:xmlTemplates/>
    <con:parameters/>
  </con:reporting>
  <con:eventHandlers type="RequestFilter.filterRequest" name="RequestFilter.filterRequest">
    <con:script>// Sample event script to add custom HTTP header to all outgoing REST, SOAP and HTTP(S) calls
// This code is often used for adding custom authentication to ReadyAPI functional tests

// If hardcoding the token, uncomment and change line 5
// token = '4567'

// If your token is parameterized in Project level custom property, uncomment line 8
// token = request.parent.testCase.testSuite.project.getProperty('auth_token').getValue()

// To modify all outgoing calls, remove comments from lines 11 to 16
// headers = request.requestHeaders
// if (headers.containsKey('auth_token2') == false) {
//   headers.put('auth_token2', token)
//   request.requestHeaders = headers
// }</con:script>
  </con:eventHandlers>
  <con:eventHandlers type="TestRunListener.afterStep" name="TestRunListener.afterStep">
    <con:script>// Save all test step results into files
// Change the directory path in line 5 to a location where you want to store details
// then uncomment lines 5 to 10

// filePath = 'C:\\tempOutputDirectory\\'
// fos = new java.io.FileOutputStream(filePath + testStepResult.testStep.label + '.txt', true)
// pw = new java.io.PrintWriter(fos)
// testStepResult.writeTo(pw)
// pw.close()
// fos.close()</con:script>
  </con:eventHandlers>
  <con:authRepository/>
  <con:tags/>
</con:soapui-project>